MANIFEST.in
setup.cfg
setup.py
jetee/__init__.py
jetee.egg-info/PKG-INFO
jetee.egg-info/SOURCES.txt
jetee.egg-info/dependency_links.txt
jetee.egg-info/entry_points.txt
jetee.egg-info/requires.txt
jetee.egg-info/top_level.txt
jetee/base/__init__.py
jetee/base/config.py
jetee/base/config_factories_manager.py
jetee/base/config_factory.py
jetee/base/deployment_manager.py
jetee/base/exceptions.py
jetee/base/process.py
jetee/base/project.py
jetee/base/service.py
jetee/base/tests/__init__.py
jetee/base/tests/fixtures.py
jetee/base/tests/test_config.py
jetee/base/tests/test_config_factories_manager.py
jetee/base/tests/test_config_factory.py
jetee/base/tests/test_deployment_manager.py
jetee/base/tests/test_process.py
jetee/base/tests/test_project.py
jetee/base/tests/test_service.py
jetee/common/__init__.py
jetee/common/discoverer.py
jetee/common/shell.py
jetee/common/user_configuration.py
jetee/common/utils.py
jetee/common/config_factories/__init__.py
jetee/common/config_factories/os/__init__.py
jetee/common/config_factories/os/apt.py
jetee/common/config_factories/os/docker.py
jetee/common/config_factories/os/nginx.py
jetee/common/config_factories/os/python.py
jetee/common/config_factories/os/redis.py
jetee/common/config_factories/project/__init__.py
jetee/common/config_factories/project/apt.py
jetee/common/config_factories/project/cron.py
jetee/common/config_factories/project/directories.py
jetee/common/config_factories/project/django.py
jetee/common/config_factories/project/git.py
jetee/common/config_factories/project/pip.py
jetee/common/config_factories/project/ssh.py
jetee/common/config_factories/project/supervisor.py
jetee/common/config_factories/service/__init__.py
jetee/common/config_factories/service/docker.py
jetee/common/config_factories/service/hosts.py
jetee/common/config_factories/service/nginx.py
jetee/common/config_factories/service/supervisor.py
jetee/common/config_factories/service/tests/__init__.py
jetee/common/config_factories/service/tests/test_docker.py
jetee/common/config_factories/service/tests/test_nginx.py
jetee/common/config_factories/service/tests/test_supervisor.py
jetee/processes/__init__.py
jetee/processes/celery.py
