Metadata-Version: 1.1
Name: jetee
Version: 0.7.3
Summary: Lightweight deployment tool
Home-page: https://github.com/WhackoJacko/Jetee.git
Author: Sergey Dubinin
Author-email: whackojacko.ru@gmail.com
License: UNKNOWN
Download-URL: https://github.com/whackojacko/jetee/tarball/v0.7.2/
Platform: UNKNOWN
